efb_wechat_slave/__init__.py
efb_wechat_slave/__version__.py
efb_wechat_slave/chats.py
efb_wechat_slave/constants.py
efb_wechat_slave/slave_message.py
efb_wechat_slave/utils.py
efb_wechat_slave/wizard.py
efb_wechat_slave/locale/az_AZ/LC_MESSAGES/efb_wechat_slave.po
efb_wechat_slave/locale/en/LC_MESSAGES/efb_wechat_slave.po
efb_wechat_slave/locale/en_US/LC_MESSAGES/efb_wechat_slave.po
efb_wechat_slave/locale/es_AR/LC_MESSAGES/efb_wechat_slave.po
efb_wechat_slave/locale/es_VE/LC_MESSAGES/efb_wechat_slave.po
efb_wechat_slave/locale/id_ID/LC_MESSAGES/efb_wechat_slave.po
efb_wechat_slave/locale/it_IT/LC_MESSAGES/efb_wechat_slave.po
efb_wechat_slave/locale/ja_JP/LC_MESSAGES/efb_wechat_slave.po
efb_wechat_slave/locale/ms_MY/LC_MESSAGES/efb_wechat_slave.po
efb_wechat_slave/locale/ro_RO/LC_MESSAGES/efb_wechat_slave.po
efb_wechat_slave/locale/tr_TR/LC_MESSAGES/efb_wechat_slave.po
efb_wechat_slave/locale/zh_CN/LC_MESSAGES/efb_wechat_slave.po
efb_wechat_slave/locale/zh_TW/LC_MESSAGES/efb_wechat_slave.po
efb_wechat_slave/vendor/__init__.py
efb_wechat_slave/vendor/itchat/__init__.py
efb_wechat_slave/vendor/itchat/config.py
efb_wechat_slave/vendor/itchat/content.py
efb_wechat_slave/vendor/itchat/core.py
efb_wechat_slave/vendor/itchat/log.py
efb_wechat_slave/vendor/itchat/returnvalues.py
efb_wechat_slave/vendor/itchat/utils.py
efb_wechat_slave/vendor/itchat/async_components/__init__.py
efb_wechat_slave/vendor/itchat/async_components/contact.py
efb_wechat_slave/vendor/itchat/async_components/hotreload.py
efb_wechat_slave/vendor/itchat/async_components/login.py
efb_wechat_slave/vendor/itchat/async_components/messages.py
efb_wechat_slave/vendor/itchat/async_components/register.py
efb_wechat_slave/vendor/itchat/components/__init__.py
efb_wechat_slave/vendor/itchat/components/contact.py
efb_wechat_slave/vendor/itchat/components/hotreload.py
efb_wechat_slave/vendor/itchat/components/login.py
efb_wechat_slave/vendor/itchat/components/messages.py
efb_wechat_slave_itchat_uos-2.0.8.dist-info/AUTHORS
efb_wechat_slave_itchat_uos-2.0.8.dist-info/LICENSE.md
efb_wechat_slave_itchat_uos-2.0.8.dist-info/METADATA
efb_wechat_slave_itchat_uos-2.0.8.dist-info/WHEEL
efb_wechat_slave_itchat_uos-2.0.8.dist-info/entry_points.txt
efb_wechat_slave_itchat_uos-2.0.8.dist-info/top_level.txt
efb_wechat_slave_itchat_uos-2.0.8.dist-info/RECORD
